bvslusa/__init__.py
bvslusa/_modidx.py
bvslusa/evaluate.py
bvslusa/metrics.py
bvslusa/ratings.py
bvslusa/validate.py
bvslusa-0.0.2.dist-info/LICENSE
bvslusa-0.0.2.dist-info/METADATA
bvslusa-0.0.2.dist-info/WHEEL
bvslusa-0.0.2.dist-info/entry_points.txt
bvslusa-0.0.2.dist-info/top_level.txt
bvslusa-0.0.2.dist-info/RECORD
