Metadata-Version: 2.1
Name: bvslusa
Version: 0.0.2
Summary: Functions to work with BVS enriched data
Home-page: https://github.com/datarisk-io/bvslusa
Author: João Nogueira
Author-email: joao.nogueira@datarisk.io
License: Apache Software License 2.0
Keywords: nbdev jupyter notebook python
Classifier: Development Status :: 4 - Beta
Classifier: Intended Audience :: Developers
Classifier: Natural Language :: English
Classifier: Programming Language :: Python :: 3.7
Classifier: Programming Language :: Python :: 3.8
Classifier: Programming Language :: Python :: 3.9
Classifier: Programming Language :: Python :: 3.10
Classifier: License :: OSI Approved :: Apache Software License
Requires-Python: >=3.7
License-File: LICENSE
Requires-Dist: fastcore
Requires-Dist: pandas
Requires-Dist: numpy
Requires-Dist: scikit-learn
Requires-Dist: optbinning
Provides-Extra: dev
